messenger/__init__.py
messenger/__pycache__/__init__.cpython-38.pyc
messenger/client/__init__.py
messenger/client/click_label.py
messenger/client/client_commands.py
messenger/client/client_content.py
messenger/client/client_ui.py
messenger/client/client_ui.ui
messenger/client/messenger.py
messenger/client/preferences.py
messenger/client/preferences_ui.py
messenger/client/preferences_ui.ui
messenger/client/style.qss
messenger/client/style_sheet.py
messenger/client/__pycache__/__init__.cpython-38.pyc
messenger/client/__pycache__/click_label.cpython-38.pyc
messenger/client/__pycache__/client_commands.cpython-38.pyc
messenger/client/__pycache__/client_content.cpython-38.pyc
messenger/client/__pycache__/client_ui.cpython-38.pyc
messenger/client/__pycache__/messenger.cpython-38.pyc
messenger/client/__pycache__/preferences.cpython-38.pyc
messenger/client/__pycache__/preferences_ui.cpython-38.pyc
messenger/client/__pycache__/style_sheet.cpython-38.pyc
messenger/client/images/Icon.png
messenger/client/images/critical.png
messenger/client/images/eye.png
messenger/client/images/hidden.png
messenger/client/images/information.png
messenger/client/images/question.png
messenger/client/images/server-is-off.png
messenger/client/images/server-is-on.png
messenger/server/__init__.py
messenger/server/codec.py
messenger/server/database.py
messenger/server/messages_overflow.py
messenger/server/server.py
messenger/server/server_commands.py
messenger/server/__pycache__/__init__.cpython-38.pyc
messenger/server/__pycache__/codec.cpython-38.pyc
messenger/server/__pycache__/database.cpython-38.pyc
messenger/server/__pycache__/messages_overflow.cpython-38.pyc
messenger/server/__pycache__/server.cpython-38.pyc
messenger/server/__pycache__/server_commands.cpython-38.pyc
py_messenger-1.2.1.dist-info/LICENSE.txt
py_messenger-1.2.1.dist-info/METADATA
py_messenger-1.2.1.dist-info/WHEEL
py_messenger-1.2.1.dist-info/top_level.txt
py_messenger-1.2.1.dist-info/RECORD
